pygradecode/__init__.py
pygradecode/ast_to_xml.py
pygradecode/find_arguments.py
pygradecode/find_attributes.py
pygradecode/find_functions.py
pygradecode/find_operators.py
pygradecode/find_utils.py
pygradecode/grade_code_found.py
pygradecode/highlight_text.py
pygradecode/xml_utils.py
pygradethis/__init__.py
pygradethis/check_functions.py
pygradethis/conditions.py
pygradethis/feedback.py
pygradethis/formatters.py
pygradethis/grade_code.py
pygradethis/grade_result.py
pygradethis/message_generators.py
pygradethis/pygradethis_exercise_checker.py
pygradethis/python_grader.py
pygradethis/result_checker.py
pygradethis/utils.py
pygradethis-0.4.0.dist-info/LICENSE
pygradethis-0.4.0.dist-info/METADATA
pygradethis-0.4.0.dist-info/WHEEL
pygradethis-0.4.0.dist-info/top_level.txt
pygradethis-0.4.0.dist-info/RECORD
