Metadata-Version: 2.1
Name: pygradethis
Version: 0.4.0
Summary: Python autograder to facilitate code output and static code checking.
Home-page: https://github.com/nischalshrestha/pygradethis
Author: Nischal Shrestha
Author-email: nsrocker92@gmail.com
License: MIT
Keywords: autograder,education
Platform: UNKNOWN
Classifier: Intended Audience :: Education
Classifier: License :: OSI Approved :: MIT License
Classifier: Operating System :: Unix
Classifier: Operating System :: MacOS
Classifier: Programming Language :: Python :: 3.10
Classifier: Topic :: Education
Requires-Python: >=3.10
License-File: LICENSE
Requires-Dist: lxml
Requires-Dist: rich
Requires-Dist: pandas
Provides-Extra: dev
Requires-Dist: pytest ; extra == 'dev'
Requires-Dist: pytest-cov ; extra == 'dev'
Requires-Dist: ruff ; extra == 'dev'
Requires-Dist: mypy ; extra == 'dev'
Requires-Dist: types-lxml ; extra == 'dev'
Requires-Dist: sphinx ; extra == 'dev'
Requires-Dist: sphinx-autodoc-typehints ; extra == 'dev'
Requires-Dist: myst-parser ; extra == 'dev'
Requires-Dist: sphinx-book-theme ; extra == 'dev'
Provides-Extra: extras
Requires-Dist: plotnine ; extra == 'extras'
